douban/__init__.py
douban/__main__.py
douban/album.py
douban/command.py
douban/photo.py
douban/thread_utils.py
douban/vars.py
douban/store/__init__.py
douban/store/file_utils.py
lilyzt_douban_dl-1.0.0.dist-info/LICENSE
lilyzt_douban_dl-1.0.0.dist-info/METADATA
lilyzt_douban_dl-1.0.0.dist-info/WHEEL
lilyzt_douban_dl-1.0.0.dist-info/entry_points.txt
lilyzt_douban_dl-1.0.0.dist-info/top_level.txt
lilyzt_douban_dl-1.0.0.dist-info/RECORD
