Metadata-Version: 2.1
Name: lilyzt-douban-dl
Version: 1.0.0
Summary: Douban Photo Downloader
Home-page: https://gitlab.com/hxlhxl2012/douban-dl
Author: hxlhxl2012
Author-email: UNKNOWN
License: MIT
Keywords: douban downloader
Platform: UNKNOWN
Requires-Dist: bs4
Requires-Dist: requests
